[
{
    "title": "【プラスぺ新宿西口】新宿D5出口20秒 貸し会議室/テレワーク/オフィス　オカムラビジネスチェア ",
    "subtitle": "新宿D5出口すぐ 大型テレビ55型・FireTV オカムラチェア/動画スタジオ撮影/オフ会/少人数会議  【プラスペ新宿西口】",
    "price": "¥808〜¥2,310",
    "location": "〜6人",
    "review_score": "4.8",
    "review_count": ""
},
{
    "title": "FEEEP 新橋店",
    "subtitle": "🌟資格やお子様の勉強に🌟【新橋駅徒歩2分｜レンタル自習室｜16PS】完全個室/無料Wi-Fi/電源/31.5inモニター",
    "price": "¥739〜¥1,001",
    "location": "2m²",
    "review_score": "4.9",
    "review_count": ""
},
{
    "title": "神保町お茶の水 ウィルシャー・プレイス🍀✨神田小川町太田屋ビル✨",
    "subtitle": "神保町🚶‍♂️２分・お茶の水４分🍀最大20名/会議・商談 ・懇親会・ボドゲ・施術・飲食🍷可！全備品無料✨お得な1日プラン✨",
    "price": "¥126〜¥2,310",
    "location": "31m²",
    "review_score": "4.9",
    "review_count": ""
},
{
    "title": "上野御徒町 ウィルシャー・プレイス🍀✨佐藤ビル１階✨",
    "subtitle": "上野駅３出口🚶‍♂️3分✨御徒町駅北口🚶‍♂️３分✨１フロアー１ルーム１階🍀最大20名🍀会議・ボドゲ・懇親会🍷✨🍀1日プラン有✨",
    "price": "¥924〜¥2,541",
    "location": "40m²",
    "review_score": "5.0",
    "review_count": ""
},
{
    "title": "ゆりねこルーム 赤坂",
    "subtitle": "赤坂駅・乃木坂駅から徒歩約６分のレンタルスペース★完全個室★2025/1/11OPEN",
    "price": "¥115〜¥1,386",
    "location": "17m²",
    "review_score": "5.0",
    "review_count": ""
},
{
    "title": "大崎ブックカフェ",
    "subtitle": "大崎駅徒歩５分のレンタルスペース(会議、撮影、ワークショップ、パーティー)",
    "price": "¥3,234〜¥4,620",
    "location": "70m²",
    "review_score": "4.9",
    "review_count": ""
},
{
    "title": "ふれあい貸し会議室 大阪駅前第２ビル",
    "subtitle": "【梅田駅地下直結で最高の立地！大阪駅前第二ビル！8名利用可！】大型モニター・WiFi全て無料！ふれあい貸し会議室 梅田No132",
    "price": "¥1,074〜¥1,118",
    "location": "10m²",
    "review_score": "4.5",
    "review_count": ""
},
{
    "title": "Leaf【リーフ】京都駅前",
    "subtitle": "【京都駅４分】最大51名/高速Wi-Fi/巨大プロジェクター・モニター/マイク/飲食OK/セミナー",
    "price": "¥3,465〜¥6,930",
    "location": "60m²",
    "review_score": "4.8",
    "review_count": ""
},
{
    "title": "FEEEP　飯田橋店",
    "subtitle": "🌟資格やお子様の勉強に🌟【飯田橋駅徒歩1分｜レンタル自習室｜11PS】完全個室/無料Wi-Fi/電源/31.5inモニター",
    "price": "¥739〜¥1,001",
    "location": "2m²",
    "review_score": "4.4",
    "review_count": ""
},
{
    "title": "✨【貸し会議室】アーバンスペース神田大手町✨",
    "subtitle": "【大手町/神田駅徒歩５分】16名収容🛜光Wi-Fi🌇プロジェクター🗝️鍵無し入室可📊会議📷撮影/動画配信🃏ボドゲに最適",
    "price": "¥777〜¥2,499",
    "location": "31m²",
    "review_score": "4.8",
    "review_count": ""
},
{
    "title": "【CocoBizⅨ】銀座一丁目徒歩1分の会議室",
    "subtitle": "2025.2.NewOPEN/銀座一丁目徒歩1分/会議/オフ会/ボドゲ/撮影/40インチモニタ/Blu-ray",
    "price": "¥126〜¥1,940",
    "location": "13m²",
    "review_score": "5.0",
    "review_count": ""
},
{
    "title": "QRラウンジ 上野店〈Quiddity Room〉",
    "subtitle": "【🏠上野駅徒歩４分🏠】ボドゲ🎲特化の趣味部屋✨",
    "price": "¥577〜¥2,541",
    "location": "22m²",
    "review_score": "5.0",
    "review_count": ""
},
{
    "title": "FEEEP　飯田橋店",
    "subtitle": "🌟隙間時間の待合室に🌟【飯田橋駅徒歩1分｜飲み物持込OK｜10PS】個室/無料Wi-Fi/電源/31.5inモニター",
    "price": "¥739〜¥1,001",
    "location": "2m²",
    "review_score": "4.5",
    "review_count": ""
},
{
    "title": "ふれあい貸し会議室 渋谷幸和",
    "subtitle": "【渋谷駅1分！ヒカリエ隣！81名】プロジェクター・ホワイトボード・WiFi・無線マイク全て無料！ふれあい貸し会議室 渋谷No89",
    "price": "¥3,846〜¥10,718",
    "location": "80m²",
    "review_score": "3.8",
    "review_count": ""
},
{
    "title": "NEW！ KS9 新宿　Space　Adventure",
    "subtitle": "NEW!新宿三丁目駅徒歩3分!/最大28名/会議/セミナー/面接/懇親会/ボドゲ/女子会で利用可/飲食お酒可/貸会議室KS9新宿",
    "price": "¥115〜¥2,310",
    "location": "35m²",
    "review_score": "4.9",
    "review_count": ""
},
{
    "title": "LINKスペース船橋",
    "subtitle": "365日23時まで利用可能　静かな環境で勉強や作業に最適　テレワーク/会議/面接/撮影等/マッサージ・サロン",
    "price": "¥577〜¥1,050",
    "location": "17m²",
    "review_score": "4.8",
    "review_count": ""
},
{
    "title": "KS2新宿　会議室",
    "subtitle": "★新宿西口駅D5出口から徒歩30秒★新宿駅から徒歩2分!土足OK!飲食持込可!会議/ボドゲ/女子会で利用可能!貸会議室KS2新宿",
    "price": "¥115〜¥1,100",
    "location": "18m²",
    "review_score": "4.7",
    "review_count": ""
},
{
    "title": "KUUKAN新橋",
    "subtitle": "【NEW!】新橋徒歩4分/最大18名/Wi-Fi/会議・撮影・懇親会・パーティ・飲食可！",
    "price": "¥110〜¥2,425",
    "location": "26m²",
    "review_score": "-",
    "review_count": ""
},
{
    "title": "【プラスペ東新宿】　オフ会/ポップインアラジン/カードゲーム/ミシン3台　大きい机/ゴミ処理可能",
    "subtitle": "新宿/大久保🌸100㌅プロジェクター/オフ会/配信/作業/カードゲーム/ミシン　ゴミ回収可【プラスペ 東新宿】",
    "price": "¥865〜¥2,887",
    "location": "33m²",
    "review_score": "4.8",
    "review_count": ""
},
{
    "title": "[Good Space会議室]　神田鉄鋼5F",
    "subtitle": "神田駅徒歩1分｜最大52名着席｜懇親会・会議・研修・大型イベント｜100㌅大型スクリーン｜24時間｜ボドゲ会｜GS[57]",
    "price": "¥577〜¥5,082",
    "location": "70m²",
    "review_score": "4.8",
    "review_count": ""
}
]